LASMnemonicsID/__init__.py
LASMnemonicsID/DLIS/__init__.py
LASMnemonicsID/LAS/LAS.py
LASMnemonicsID/LAS/__init__.py
LASMnemonicsID/utils/__init__.py
LASMnemonicsID/utils/mnemonics.py
lasmnemonicsid-0.0.2.dist-info/licenses/LICENSE
lasmnemonicsid-0.0.2.dist-info/METADATA
lasmnemonicsid-0.0.2.dist-info/WHEEL
lasmnemonicsid-0.0.2.dist-info/top_level.txt
lasmnemonicsid-0.0.2.dist-info/RECORD
